bootstrap_budget/__init__.py
bootstrap_budget/account.py
bootstrap_budget/admin.py
bootstrap_budget/auth.py
bootstrap_budget/budget.py
bootstrap_budget/budget_item.py
bootstrap_budget/cli.py
bootstrap_budget/dashboard.py
bootstrap_budget/entities.py
bootstrap_budget/transaction.py
bootstrap_budget/user.py
bootstrap_budget/sample_data/__init__.py
bootstrap_budget/sample_data/account.csv
bootstrap_budget/sample_data/budget.csv
bootstrap_budget/sample_data/budget_item.csv
bootstrap_budget/sample_data/transaction.csv
bootstrap_budget/static/android-chrome-192x192.png
bootstrap_budget/static/android-chrome-512x512.png
bootstrap_budget/static/apple-touch-icon.png
bootstrap_budget/static/bootstrap-icons.min.css
bootstrap_budget/static/bootstrap.bundle.min.js
bootstrap_budget/static/bootstrap.min.css
bootstrap_budget/static/favicon-16x16.png
bootstrap_budget/static/favicon-32x32.png
bootstrap_budget/static/favicon.ico
bootstrap_budget/static/login.css
bootstrap_budget/static/main.css
bootstrap_budget/static/site.webmanifest
bootstrap_budget/static/fonts/bootstrap-icons.woff
bootstrap_budget/static/fonts/bootstrap-icons.woff2
bootstrap_budget/static/fonts/glyphicons-halflings-regular.eot
bootstrap_budget/static/fonts/glyphicons-halflings-regular.svg
bootstrap_budget/static/fonts/glyphicons-halflings-regular.ttf
bootstrap_budget/static/fonts/glyphicons-halflings-regular.woff
bootstrap_budget/static/fonts/glyphicons-halflings-regular.woff2
bootstrap_budget/static/images/bootstrap-logo-000000-hi-res-v2.png
bootstrap_budget/static/images/bootstrap-logo-000000-v2.jpeg
bootstrap_budget/static/images/bootstrap-logo-000000-v2.pdf
bootstrap_budget/static/images/bootstrap-logo-000000-v2.png
bootstrap_budget/static/images/bootstrap-logo-000000-v2.svg
bootstrap_budget/static/images/bootstrap-logo-ffffff-v2.png
bootstrap_budget/static/images/bootstrap-logo-ffffff-v2.xcf
bootstrap_budget/static/images/bootstrap-logo-mini-000000-hi-res-v2.png
bootstrap_budget-0.1.7.dist-info/LICENSE
bootstrap_budget-0.1.7.dist-info/METADATA
bootstrap_budget-0.1.7.dist-info/WHEEL
bootstrap_budget-0.1.7.dist-info/entry_points.txt
bootstrap_budget-0.1.7.dist-info/top_level.txt
bootstrap_budget-0.1.7.dist-info/RECORD
