Metadata-Version: 2.1
Name: bootstrap-budget
Version: 0.1.7
Summary: A simple financial application to help you pull your budget up by its bootstraps.
Author-email: forgineer <blake.phillips86@gmail.com>
License: MIT License
Project-URL: Homepage, https://forgineer.pythonanywhere.com/bootstrap-budget
Project-URL: Documentation, https://forgineer.pythonanywhere.com/bootstrap-budget
Project-URL: Repository, https://github.com/forgineer/bootstrap-budget
Project-URL: Issues, https://github.com/forgineer/bootstrap-budget/issues
Keywords: personal budget,budgeting,web app
Classifier: Development Status :: 1 - Planning
Classifier: Framework :: Flask
Classifier: Intended Audience :: End Users/Desktop
Classifier: License :: OSI Approved :: MIT License
Classifier: Operating System :: OS Independent
Classifier: Programming Language :: Python :: 3
Classifier: Topic :: Office/Business :: Financial
Requires-Python: >=3.8
License-File: LICENSE
Requires-Dist: blinker ==1.7.0
Requires-Dist: click ==8.1.7
Requires-Dist: colorama ==0.4.6
Requires-Dist: Flask ==2.3.3
Requires-Dist: itsdangerous ==2.1.2
Requires-Dist: Jinja2 ==3.1.3
Requires-Dist: MarkupSafe ==2.1.5
Requires-Dist: pony ==0.7.17
Requires-Dist: Werkzeug ==3.0.1
Provides-Extra: pypi_deploy
Requires-Dist: build ; extra == 'pypi_deploy'
Requires-Dist: twine ; extra == 'pypi_deploy'
